varys/__init__.py
varys/EventBuilder.py
varys/FileWriter.py
varys/LogParser.py
varys/util.py
varys-0.5.2.dist-info/DESCRIPTION.rst
varys-0.5.2.dist-info/METADATA
varys-0.5.2.dist-info/metadata.json
varys-0.5.2.dist-info/RECORD
varys-0.5.2.dist-info/top_level.txt
varys-0.5.2.dist-info/WHEEL
