Metadata-Version: 2.0
Name: varys
Version: 0.5.2
Summary: For parsing and reformatting behavioral event logs.
Home-page: https://github.com/beOn/varys
Author: Ben Acland
Author-email: benacland@gmail.com
License: BSD
Keywords: behavioral
Platform: UNKNOWN
Classifier: Development Status :: 2 - Pre-Alpha
Classifier: Topic :: Scientific/Engineering :: Information Analysis
Classifier: License :: OSI Approved :: BSD License
Classifier: Intended Audience :: Science/Research
Requires-Dist: scipy
Requires-Dist: chardet
